sktalk/__init__.py
sktalk/corpus/__init__.py
sktalk/corpus/conversation.py
sktalk/corpus/corpus.py
sktalk/corpus/participant.py
sktalk/corpus/utterance.py
sktalk/corpus/parsing/__init__.py
sktalk/corpus/parsing/cha.py
sktalk/corpus/parsing/csv.py
sktalk/corpus/parsing/eaf.py
sktalk/corpus/parsing/parser.py
sktalk/corpus/parsing/xml.py
sktalk/corpus/write/__init__.py
sktalk/corpus/write/writer.py
scikit_talk-0.1.1.dist-info/LICENSE
scikit_talk-0.1.1.dist-info/METADATA
scikit_talk-0.1.1.dist-info/NOTICE
scikit_talk-0.1.1.dist-info/WHEEL
scikit_talk-0.1.1.dist-info/top_level.txt
scikit_talk-0.1.1.dist-info/RECORD
