Metadata-Version: 2.1
Name: scikit-talk
Version: 0.1.1
Summary: Short description of package
Home-page: https://github.com/elpaco-escience/scikit-talk
Author: Barbara Vreede
Author-email: b.vreede@gmail.com
Project-URL: Bug Tracker, https://github.com/elpaco-escience/scikit-talk/issues
Keywords: conversation,language corpora,turn-taking
Classifier: Development Status :: 2 - Pre-Alpha
Classifier: Intended Audience :: Developers
Classifier: License :: OSI Approved :: Apache Software License
Classifier: Natural Language :: English
Classifier: Programming Language :: Python :: 3
Classifier: Programming Language :: Python :: 3.9
Classifier: Programming Language :: Python :: 3.10
Classifier: Programming Language :: Python :: 3.11
Requires-Python: >=3.9
License-File: LICENSE
License-File: NOTICE
Requires-Dist: pandas >=2.0.0
Requires-Dist: pylangacq ~=0.19.0
Requires-Dist: pympi-ling ~=1.70.2
Provides-Extra: dev
Requires-Dist: autopep8 ; extra == 'dev'
Requires-Dist: bump2version ; extra == 'dev'
Requires-Dist: coverage[toml] ; extra == 'dev'
Requires-Dist: prospector[with_pyroma] ; extra == 'dev'
Requires-Dist: isort ; extra == 'dev'
Requires-Dist: nbsphinx ; extra == 'dev'
Requires-Dist: pytest ; extra == 'dev'
Requires-Dist: pytest-cov ; extra == 'dev'
Requires-Dist: sphinx ; extra == 'dev'
Requires-Dist: sphinx-rtd-theme ; extra == 'dev'
Requires-Dist: sphinx-autoapi ; extra == 'dev'
Requires-Dist: tox ; extra == 'dev'
Requires-Dist: myst-parser ; extra == 'dev'
Provides-Extra: publishing
Requires-Dist: twine ; extra == 'publishing'
Requires-Dist: wheel ; extra == 'publishing'
